crtsh/__init__.py
crtsh/crtsh.py
py_crtsh-0.0.4.dist-info/LICENSE
py_crtsh-0.0.4.dist-info/METADATA
py_crtsh-0.0.4.dist-info/WHEEL
py_crtsh-0.0.4.dist-info/top_level.txt
py_crtsh-0.0.4.dist-info/RECORD
