Metadata-Version: 2.1
Name: py-crtsh
Version: 0.0.4
Summary: A simple package to do basic queries of crt.sh
Home-page: https://github.com/PlantDaddy/py-crtsh
Author: Plant Daddy
Author-email: CqP5TZ77NYBf5uQt@protonmail.com
License: BSD
Project-URL: Tracker, https://github.com/PlantDaddy/py-crtsh
Platform: UNKNOWN
Classifier: Programming Language :: Python :: 3
Classifier: License :: OSI Approved :: BSD License
Classifier: Operating System :: OS Independent
Requires-Python: >=3.6
Requires-Dist: scrapy
Requires-Dist: requests
